appointments/__init__.py
appointments/appointments.py
berlin_appointment_finder-2.0.0.data/scripts/appointments
berlin_appointment_finder-2.0.0.dist-info/licenses/LICENSE
berlin_appointment_finder-2.0.0.dist-info/METADATA
berlin_appointment_finder-2.0.0.dist-info/WHEEL
berlin_appointment_finder-2.0.0.dist-info/top_level.txt
berlin_appointment_finder-2.0.0.dist-info/RECORD
