Metadata-Version: 2.4
Name: berlin-appointment-finder
Version: 2.0.0
Summary: Finds appointments at the Berlin Bürgeramt, broadcasts them via websockets
Home-page: https://allaboutberlin.com/tools/appointment-finder
Author: Nicolas Bouliane
Author-email: contact@nicolasbouliane.com
License: MIT
Project-URL: Documentation, https://github.com/All-About-Berlin/burgeramt-appointments
Project-URL: Funding, https://allaboutberlin.com/donate
Project-URL: Source Code, https://github.com/All-About-Berlin/burgeramt-appointments
Project-URL: Issues, https://github.com/All-About-Berlin/burgeramt-appointments/issues
Requires-Python: >=3.10
License-File: LICENSE
Requires-Dist: chime==0.7.0
Requires-Dist: playwright==1.55.0
Requires-Dist: pytz
Requires-Dist: websockets==14.2
Dynamic: author
Dynamic: author-email
Dynamic: description
Dynamic: description-content-type
Dynamic: home-page
Dynamic: license
Dynamic: license-file
Dynamic: project-url
Dynamic: requires-dist
Dynamic: requires-python
Dynamic: summary
